devtools/conda.recipe/build_env.yml
devtools/conda.recipe/meta.yaml
pytcs/__init__.py
pytcs/exceptions.py
pytcs/helpers.py
pytcs/pytcs.py
pytcs-0.2.2.dist-info/licenses/LICENSE
pytcs-0.2.2.dist-info/METADATA
pytcs-0.2.2.dist-info/WHEEL
pytcs-0.2.2.dist-info/top_level.txt
pytcs-0.2.2.dist-info/RECORD
