Metadata-Version: 2.4
Name: pytcs
Version: 0.2.2
Summary: Python API for processing TwinCAT Scope data files
Author-email: Çağtay Fabry <cagtay.fabry@bam.de>
Project-URL: bug_tracker, https://github.com/CagtayFabry/pytcs/issues
Project-URL: repository, https://github.com/CagtayFabry/pytcs
Keywords: file reader,TwinCAT,TwinCAT Scope
Classifier: Development Status :: 4 - Beta
Classifier: Intended Audience :: Science/Research
Classifier: Natural Language :: English
Classifier: Operating System :: OS Independent
Classifier: Programming Language :: Python
Classifier: Programming Language :: Python :: 3 :: Only
Classifier: Programming Language :: Python :: 3.10
Classifier: Programming Language :: Python :: 3.11
Classifier: Programming Language :: Python :: 3.12
Classifier: Programming Language :: Python :: 3.13
Classifier: Programming Language :: Python :: 3.14
Requires-Python: >=3.10
License-File: LICENSE
Requires-Dist: bidict
Requires-Dist: numpy>=2
Requires-Dist: pandas>=2
Requires-Dist: polars>=1.21
Provides-Extra: all
Requires-Dist: bottleneck>=1.3; extra == "all"
Requires-Dist: netcdf4<1.7.4; extra == "all"
Requires-Dist: xarray>=0.15; extra == "all"
Provides-Extra: export
Requires-Dist: dicttoxml; extra == "export"
Requires-Dist: pyyaml; extra == "export"
Provides-Extra: test
Requires-Dist: netcdf4<1.7.4; extra == "test"
Requires-Dist: pytest; extra == "test"
Requires-Dist: pytest-cov; extra == "test"
Requires-Dist: pytest-xdist; extra == "test"
Requires-Dist: xarray; extra == "test"
Dynamic: license-file
